pyneurorg/__init__.py
pyneurorg/analysis/__init__.py
pyneurorg/analysis/calcium_analysis.py
pyneurorg/analysis/spike_analysis.py
pyneurorg/analysis/network_inference/__init__.py
pyneurorg/analysis/network_inference/base_inferrer.py
pyneurorg/analysis/network_inference/calcium_based_inference.py
pyneurorg/analysis/network_inference/spike_based_inference.py
pyneurorg/core/__init__.py
pyneurorg/core/network_builder.py
pyneurorg/core/neuron_models.py
pyneurorg/core/synapse_models.py
pyneurorg/electrophysiology/__init__.py
pyneurorg/electrophysiology/brian_monitors.py
pyneurorg/electrophysiology/stimulus_generator.py
pyneurorg/electrophysiology/data_persistence/__init__.py
pyneurorg/electrophysiology/data_persistence/db_schema.py
pyneurorg/electrophysiology/data_persistence/persistent_simulator.py
pyneurorg/electrophysiology/data_persistence/sqlite_reader.py
pyneurorg/electrophysiology/data_persistence/sqlite_writer.py
pyneurorg/mea/__init__.py
pyneurorg/mea/mea.py
pyneurorg/organoid/__init__.py
pyneurorg/organoid/organoid.py
pyneurorg/organoid/spatial.py
pyneurorg/plasticity/__init__.py
pyneurorg/plasticity/base_plasticity_rule.py
pyneurorg/plasticity/growth_guidance.py
pyneurorg/plasticity/homeostatic.py
pyneurorg/plasticity/stdp.py
pyneurorg/plasticity/structural_plasticity.py
pyneurorg/simulation/__init__.py
pyneurorg/simulation/simulator.py
pyneurorg/tests/__init__.py
pyneurorg/tests/analysis/__init__.py
pyneurorg/tests/analysis/test_spike_analysis.py
pyneurorg/tests/analysis/network_inference/__init__.py
pyneurorg/tests/analysis/network_inference/test_spike_based_inference.py
pyneurorg/tests/core/__init__.py
pyneurorg/tests/core/test_neuron_models.py
pyneurorg/tests/electrophysiology/__init__.py
pyneurorg/tests/electrophysiology/test_stimulus_generator.py
pyneurorg/tests/electrophysiology/data_persistence/__init__.py
pyneurorg/tests/electrophysiology/data_persistence/test_sqlite_writer.py
pyneurorg/tests/mea/__init__.py
pyneurorg/tests/mea/test_mea.py
pyneurorg-0.2.0.dist-info/METADATA
pyneurorg-0.2.0.dist-info/WHEEL
pyneurorg-0.2.0.dist-info/top_level.txt
pyneurorg-0.2.0.dist-info/RECORD
